[
  {
    "id": "R17_123",
    "content": "Ensure all user instructions are followed and prompts are documented in Prompt.md",
    "project": "Damiloju_fiscaflow",
    "file": "instruction-compliance.mdc",
    "first_level": "AI Collaboration Specifications",
    "second_level": "AI Behavior & Decision Strategies"
  },
  {
    "id": "R17_124",
    "content": "Document all user prompts in Prompt.md",
    "project": "Damiloju_fiscaflow",
    "file": "instruction-compliance.mdc",
    "first_level": "AI Collaboration Specifications",
    "second_level": "AI Output Content Guidelines"
  },
  {
    "id": "R17_125",
    "content": "Follow user instructions precisely",
    "project": "Damiloju_fiscaflow",
    "file": "instruction-compliance.mdc",
    "first_level": "AI Collaboration Specifications",
    "second_level": "AI Behavior & Decision Strategies"
  },
  {
    "id": "R17_126",
    "content": "Track progress and decisions",
    "project": "Damiloju_fiscaflow",
    "file": "instruction-compliance.mdc",
    "first_level": "Development Workflow & Project Management",
    "second_level": "Project Documentation"
  },
  {
    "id": "R17_127",
    "content": "Update Prompt.md with each new instruction",
    "project": "Damiloju_fiscaflow",
    "file": "instruction-compliance.mdc",
    "first_level": "AI Collaboration Specifications",
    "second_level": "AI Context Management"
  },
  {
    "id": "R17_128",
    "content": "Maintain conversation timeline",
    "project": "Damiloju_fiscaflow",
    "file": "instruction-compliance.mdc",
    "first_level": "AI Collaboration Specifications",
    "second_level": "AI Context Management"
  },
  {
    "id": "R17_129",
    "content": "Record key decisions and rationale",
    "project": "Damiloju_fiscaflow",
    "file": "instruction-compliance.mdc",
    "first_level": "Development Workflow & Project Management",
    "second_level": "Project Documentation"
  },
  {
    "id": "R17_130",
    "content": "Follow conventional commit rule for all changes",
    "project": "Damiloju_fiscaflow",
    "file": "instruction-compliance.mdc",
    "first_level": "Development Workflow & Project Management",
    "second_level": "Version Control"
  },
  {
    "id": "R17_131",
    "content": "Run tests before committing: make test",
    "project": "Damiloju_fiscaflow",
    "file": "instruction-compliance.mdc",
    "first_level": "Quality Assurance",
    "second_level": "Testing Strategy"
  },
  {
    "id": "R17_132",
    "content": "Commit changes immediately after file modifications",
    "project": "Damiloju_fiscaflow",
    "file": "instruction-compliance.mdc",
    "first_level": "Development Workflow & Project Management",
    "second_level": "Version Control"
  },
  {
    "id": "R17_133",
    "content": "When receiving new instructions, add them to Prompt.md under \"Conversation Timeline\"",
    "project": "Damiloju_fiscaflow",
    "file": "instruction-compliance.mdc",
    "first_level": "AI Collaboration Specifications",
    "second_level": "AI Context Management"
  },
  {
    "id": "R17_134",
    "content": "Include context, outcome, and any decisions made",
    "project": "Damiloju_fiscaflow",
    "file": "instruction-compliance.mdc",
    "first_level": "Development Workflow & Project Management",
    "second_level": "Project Documentation"
  },
  {
    "id": "R17_135",
    "content": "Update \"Pending Tasks\" and \"Current State\" sections",
    "project": "Damiloju_fiscaflow",
    "file": "instruction-compliance.mdc",
    "first_level": "Development Workflow & Project Management",
    "second_level": "Project Documentation"
  },
  {
    "id": "R17_136",
    "content": "Ensure all technical decisions are recorded",
    "project": "Damiloju_fiscaflow",
    "file": "instruction-compliance.mdc",
    "first_level": "Development Workflow & Project Management",
    "second_level": "Project Documentation"
  },
  {
    "id": "R17_137",
    "content": "When making file changes, run tests first: make test",
    "project": "Damiloju_fiscaflow",
    "file": "instruction-compliance.mdc",
    "first_level": "Quality Assurance",
    "second_level": "Testing Strategy"
  },
  {
    "id": "R17_138",
    "content": "Stage changes immediately: git add .",
    "project": "Damiloju_fiscaflow",
    "file": "instruction-compliance.mdc",
    "first_level": "Development Workflow & Project Management",
    "second_level": "Version Control"
  },
  {
    "id": "R17_139",
    "content": "Commit using conventional format: git commit -m \"type(scope): description\"",
    "project": "Damiloju_fiscaflow",
    "file": "instruction-compliance.mdc",
    "first_level": "Development Workflow & Project Management",
    "second_level": "Version Control"
  },
  {
    "id": "R17_140",
    "content": "Update Prompt.md with the outcome",
    "project": "Damiloju_fiscaflow",
    "file": "instruction-compliance.mdc",
    "first_level": "AI Collaboration Specifications",
    "second_level": "AI Context Management"
  },
  {
    "id": "R17_141",
    "content": "Unit tests must pass: make test-unit",
    "project": "Damiloju_fiscaflow",
    "file": "instruction-compliance.mdc",
    "first_level": "Quality Assurance",
    "second_level": "Testing Strategy"
  },
  {
    "id": "R17_142",
    "content": "Integration tests must pass: make test-integration",
    "project": "Damiloju_fiscaflow",
    "file": "instruction-compliance.mdc",
    "first_level": "Quality Assurance",
    "second_level": "Testing Strategy"
  },
  {
    "id": "R17_143",
    "content": "All tests must pass: make test",
    "project": "Damiloju_fiscaflow",
    "file": "instruction-compliance.mdc",
    "first_level": "Quality Assurance",
    "second_level": "Testing Strategy"
  },
  {
    "id": "R17_144",
    "content": "If tests fail, fix the issues before committing",
    "project": "Damiloju_fiscaflow",
    "file": "instruction-compliance.mdc",
    "first_level": "Quality Assurance",
    "second_level": "Testing Strategy"
  },
  {
    "id": "R17_145",
    "content": "Conventional Commit Format: feat: new feature",
    "project": "Damiloju_fiscaflow",
    "file": "instruction-compliance.mdc",
    "first_level": "Development Workflow & Project Management",
    "second_level": "Version Control"
  },
  {
    "id": "R17_146",
    "content": "Conventional Commit Format: fix: bug fix",
    "project": "Damiloju_fiscaflow",
    "file": "instruction-compliance.mdc",
    "first_level": "Development Workflow & Project Management",
    "second_level": "Version Control"
  },
  {
    "id": "R17_147",
    "content": "Conventional Commit Format: docs: documentation",
    "project": "Damiloju_fiscaflow",
    "file": "instruction-compliance.mdc",
    "first_level": "Development Workflow & Project Management",
    "second_level": "Version Control"
  },
  {
    "id": "R17_148",
    "content": "Conventional Commit Format: style: formatting",
    "project": "Damiloju_fiscaflow",
    "file": "instruction-compliance.mdc",
    "first_level": "Development Workflow & Project Management",
    "second_level": "Version Control"
  },
  {
    "id": "R17_149",
    "content": "Conventional Commit Format: refactor: code restructuring",
    "project": "Damiloju_fiscaflow",
    "file": "instruction-compliance.mdc",
    "first_level": "Development Workflow & Project Management",
    "second_level": "Version Control"
  },
  {
    "id": "R17_150",
    "content": "Conventional Commit Format: test: testing",
    "project": "Damiloju_fiscaflow",
    "file": "instruction-compliance.mdc",
    "first_level": "Development Workflow & Project Management",
    "second_level": "Version Control"
  },
  {
    "id": "R17_151",
    "content": "Conventional Commit Format: chore: maintenance",
    "project": "Damiloju_fiscaflow",
    "file": "instruction-compliance.mdc",
    "first_level": "Development Workflow & Project Management",
    "second_level": "Version Control"
  }
]
