[
  {
    "id": "R11_17",
    "content": "# Folder Stucture\n> FSD Architecture\n```plaintext\nsrc/\n |- index.css\n |- index.html\n |\n |- app/\n |   |- route/\n |   |    |- __root.tsx   tanstack-router 루트 파일\n |   |    ∟- [페이지경로]/   tanstack-router 파일 기반 라우팅\n |   ∟- main.tsx\n |\n |- entities/             데이터 단위\n |   ∟- [엔티티명]/         (예: post/, user/ )\n |         |- model/      (예: Post, PostComment, User)\n |         |- api/        (예: usePost, usePostCommnet, useUser)\n |         ∟- schema/     (예: Post, PostComment, User)\n |\n |- features/             기능 컴포넌트\n |   ∟- [기능명]/          (예: post/, auth/ )\n |         |- ui/        (예: PostCard, PostHeader, PostBody, PostList, LoginForm)\n |         |- api/       (예: usePost, usePostCommnet, login, use)\n |         ∟- schema/    (예: Post, PostComment)\n |\n ∟- shared/               공유 컴포넌트, 설정, 타입, 함수들\n     |- assets            이미지, 아이콘 등 \n     |- components\n     |     ∟- ui\n     |- api               axios 기본 객체, 인터셉터 등\n     |- utils\n     ∟- schema\n```",
    "project": "chan-ok_knowledge",
    "file": "folder-structure.mdc",
    "first_level": "Development Workflow & Project Management",
    "second_level": "Directory Structure"
  }
]
