[
  {
    "id": "R64_1",
    "content": "Prefer standalone components over modules",
    "project": "Piotr-Serwatka_RickMortyCharacters",
    "file": "project-rules.mdc",
    "first_level": "Code Implementation",
    "second_level": "Framework Usage"
  },
  {
    "id": "R64_2",
    "content": "Always use the latest Vue 3 Composition API syntax",
    "project": "Piotr-Serwatka_RickMortyCharacters",
    "file": "project-rules.mdc",
    "first_level": "Code Implementation",
    "second_level": "Framework Usage"
  },
  {
    "id": "R64_3",
    "content": "The <script setup> section must always come before <template>",
    "project": "Piotr-Serwatka_RickMortyCharacters",
    "file": "project-rules.mdc",
    "first_level": "Code Implementation",
    "second_level": "Framework Usage"
  },
  {
    "id": "R64_4",
    "content": "Use a feature-first approach (organize code by functionality, not by type)",
    "project": "Piotr-Serwatka_RickMortyCharacters",
    "file": "project-rules.mdc",
    "first_level": "Development Workflow & Project Management",
    "second_level": "Directory Structure"
  },
  {
    "id": "R64_5",
    "content": "Build small, reusable components with single responsibility",
    "project": "Piotr-Serwatka_RickMortyCharacters",
    "file": "project-rules.mdc",
    "first_level": "Architecture & Design",
    "second_level": "Design Principles & Patterns"
  },
  {
    "id": "R64_6",
    "content": "Maintain a flat component hierarchy whenever possible",
    "project": "Piotr-Serwatka_RickMortyCharacters",
    "file": "project-rules.mdc",
    "first_level": "Architecture & Design",
    "second_level": "Design Principles & Patterns"
  },
  {
    "id": "R64_7",
    "content": "Use SCSS exclusively",
    "project": "Piotr-Serwatka_RickMortyCharacters",
    "file": "project-rules.mdc",
    "first_level": "Architecture & Design",
    "second_level": "Technology Stack Selections"
  },
  {
    "id": "R64_8",
    "content": "Prefer utility classes over writing custom CSS",
    "project": "Piotr-Serwatka_RickMortyCharacters",
    "file": "project-rules.mdc",
    "first_level": "Code Implementation",
    "second_level": "Language Features"
  },
  {
    "id": "R64_9",
    "content": "Avoid inline styles unless absolutely necessary",
    "project": "Piotr-Serwatka_RickMortyCharacters",
    "file": "project-rules.mdc",
    "first_level": "Code Implementation",
    "second_level": "Language Features"
  },
  {
    "id": "R64_10",
    "content": "Always use explicit types; avoid any",
    "project": "Piotr-Serwatka_RickMortyCharacters",
    "file": "project-rules.mdc",
    "first_level": "Code Implementation",
    "second_level": "Language Features"
  },
  {
    "id": "R64_11",
    "content": "Use interfaces for complex data structures",
    "project": "Piotr-Serwatka_RickMortyCharacters",
    "file": "project-rules.mdc",
    "first_level": "Code Implementation",
    "second_level": "Language Features"
  },
  {
    "id": "R64_12",
    "content": "Enable and use strict mode in TypeScript configuration",
    "project": "Piotr-Serwatka_RickMortyCharacters",
    "file": "project-rules.mdc",
    "first_level": "Development Workflow & Project Management",
    "second_level": "Environment Configuration"
  },
  {
    "id": "R64_13",
    "content": "Use ref or reactive locally within components for simple state",
    "project": "Piotr-Serwatka_RickMortyCharacters",
    "file": "project-rules.mdc",
    "first_level": "Code Implementation",
    "second_level": "Framework Usage"
  },
  {
    "id": "R64_14",
    "content": "Use Pinia for shared or complex state",
    "project": "Piotr-Serwatka_RickMortyCharacters",
    "file": "project-rules.mdc",
    "first_level": "Code Implementation",
    "second_level": "Framework Usage"
  },
  {
    "id": "R64_15",
    "content": "Prefer immutability when managing state",
    "project": "Piotr-Serwatka_RickMortyCharacters",
    "file": "project-rules.mdc",
    "first_level": "Architecture & Design",
    "second_level": "Design Principles & Patterns"
  },
  {
    "id": "R64_16",
    "content": "Use props and emits for parent-child communication",
    "project": "Piotr-Serwatka_RickMortyCharacters",
    "file": "project-rules.mdc",
    "first_level": "Code Implementation",
    "second_level": "Framework Usage"
  },
  {
    "id": "R64_17",
    "content": "Avoid prop drilling; if necessary, use provide() and inject() — but only for configuration or dependency injection, not for dynamic data",
    "project": "Piotr-Serwatka_RickMortyCharacters",
    "file": "project-rules.mdc",
    "first_level": "Code Implementation",
    "second_level": "Framework Usage"
  },
  {
    "id": "R64_18",
    "content": "Use a centralized HttpClient for all API interactions",
    "project": "Piotr-Serwatka_RickMortyCharacters",
    "file": "project-rules.mdc",
    "first_level": "Architecture & Design",
    "second_level": "System Architecture"
  },
  {
    "id": "R64_19",
    "content": "Always handle errors in HTTP calls",
    "project": "Piotr-Serwatka_RickMortyCharacters",
    "file": "project-rules.mdc",
    "first_level": "Code Implementation",
    "second_level": "Error & Exception Handling"
  },
  {
    "id": "R64_20",
    "content": "Create dedicated services for API logic",
    "project": "Piotr-Serwatka_RickMortyCharacters",
    "file": "project-rules.mdc",
    "first_level": "Architecture & Design",
    "second_level": "System Architecture"
  },
  {
    "id": "R64_21",
    "content": "Use lazy loading for modules and components wherever applicable",
    "project": "Piotr-Serwatka_RickMortyCharacters",
    "file": "project-rules.mdc",
    "first_level": "Code Implementation",
    "second_level": "Performance Optimization"
  },
  {
    "id": "R64_22",
    "content": "Do not use jQuery or direct DOM manipulation",
    "project": "Piotr-Serwatka_RickMortyCharacters",
    "file": "project-rules.mdc",
    "first_level": "Code Implementation",
    "second_level": "Framework Usage"
  },
  {
    "id": "R64_23",
    "content": "Avoid mixing multiple state management approaches",
    "project": "Piotr-Serwatka_RickMortyCharacters",
    "file": "project-rules.mdc",
    "first_level": "Architecture & Design",
    "second_level": "Design Principles & Patterns"
  },
  {
    "id": "R64_24",
    "content": "Do not overload components with business logic",
    "project": "Piotr-Serwatka_RickMortyCharacters",
    "file": "project-rules.mdc",
    "first_level": "Architecture & Design",
    "second_level": "Design Principles & Patterns"
  },
  {
    "id": "R64_25",
    "content": "Avoid deeply nested component hierarchies",
    "project": "Piotr-Serwatka_RickMortyCharacters",
    "file": "project-rules.mdc",
    "first_level": "Architecture & Design",
    "second_level": "Design Principles & Patterns"
  },
  {
    "id": "R64_26",
    "content": "Do not place business logic inside components — move it to services",
    "project": "Piotr-Serwatka_RickMortyCharacters",
    "file": "project-rules.mdc",
    "first_level": "Architecture & Design",
    "second_level": "Design Principles & Patterns"
  }
]
