[
  {
    "id": "R65_24",
    "content": "Make simple layout using modern html and css best practices",
    "project": "quarion_poke-math",
    "file": "frontend.mdc",
    "first_level": "Architecture & Design",
    "second_level": "Design Principles & Patterns"
  },
  {
    "id": "R65_25",
    "content": "Make sure the layout is responsive",
    "project": "quarion_poke-math",
    "file": "frontend.mdc",
    "first_level": "Architecture & Design",
    "second_level": "Design References & Constraints"
  },
  {
    "id": "R65_26",
    "content": "Do NOT inline styles in html files",
    "project": "quarion_poke-math",
    "file": "frontend.mdc",
    "first_level": "Code Implementation",
    "second_level": "Code Style Conventions"
  },
  {
    "id": "R65_27",
    "content": "Use style.css for styling global sytling (theme, colors, general buttons style etc.)",
    "project": "quarion_poke-math",
    "file": "frontend.mdc",
    "first_level": "Development Workflow & Project Management",
    "second_level": "Directory Structure"
  },
  {
    "id": "R65_28",
    "content": "For component-specific styles place them directly in the .html file",
    "project": "quarion_poke-math",
    "file": "frontend.mdc",
    "first_level": "Development Workflow & Project Management",
    "second_level": "Directory Structure"
  },
  {
    "id": "R65_29",
    "content": "Make sure to use consistent styling. Before creating new style consider if existing global or component style should not be used",
    "project": "quarion_poke-math",
    "file": "frontend.mdc",
    "first_level": "Quality Assurance",
    "second_level": "Code Quality Standards"
  }
]
